mcp_feishu_bot/__init__.py
mcp_feishu_bot/bitable.py
mcp_feishu_bot/client.py
mcp_feishu_bot/drive.py
mcp_feishu_bot/main.py
mcp_feishu_bot/msg.py
mcp_feishu_bot/relay.py
mcp_feishu_bot/robot.py
mcp_feishu_bot/utils.py
mcp_feishu_bot/wiki.py
mcp_feishu_bot-0.2.6.dist-info/METADATA
mcp_feishu_bot-0.2.6.dist-info/WHEEL
mcp_feishu_bot-0.2.6.dist-info/entry_points.txt
mcp_feishu_bot-0.2.6.dist-info/top_level.txt
mcp_feishu_bot-0.2.6.dist-info/RECORD
