Metadata-Version: 2.4
Name: mcp-feishu-bot
Version: 0.2.6
Summary: A Feishu bot using MCP (Model Context Protocol)
Requires-Python: >=3.12
Requires-Dist: fastmcp>=2.12.3
Requires-Dist: lark-oapi>=1.4.23
Requires-Dist: python-socks>=2.7.2
Requires-Dist: websockets>=11.0
